Metadata-Version: 2.1
Name: pystd
Version: 0.1.2
Summary: Re-implemented Python STDLib.
Author: fswair
